ecb_scraper/__init__.py
ecb_scraper/cli.py
ecb_scraper/config.py
ecb_scraper/scraper.py
ecb_scraper-0.1.3.dist-info/LICENSE
ecb_scraper-0.1.3.dist-info/METADATA
ecb_scraper-0.1.3.dist-info/WHEEL
ecb_scraper-0.1.3.dist-info/entry_points.txt
ecb_scraper-0.1.3.dist-info/RECORD
